{
    "BaseModel.9b5448dd-2e06-42be-bd59-c2da03adc303": {
        "id": "9b5448dd-2e06-42be-bd59-c2da03adc303",
        "created_at": "2023-08-10T18:49:21.673842",
        "updated_at": "2023-08-10T18:49:21.673842",
        "__class__": "BaseModel"
    },
    "BaseModel.601abc84-d6a3-448f-a44b-d990b464ad08": {
        "id": "601abc84-d6a3-448f-a44b-d990b464ad08",
        "created_at": "2023-08-10T18:49:21.735191",
        "updated_at": "2023-08-10T18:49:21.735191",
        "__class__": "BaseModel"
    }
}